<?xml version='1.0' encoding='UTF-8'?>
<cmdows xmlns:xsi="http://www.w3.org/2001/XMLSchema-instance" xsi:noNamespaceSchemaLocation="https://bitbucket.org/imcovangent/cmdows/raw/master/schema/0.7/cmdows.xsd">
  <header>
    <creator>Imco van Gent</creator>
    <description>Mdao CMDOWS file of the well-known Sellar problem</description>
    <timestamp>2018-02-02T17:58:03.898918</timestamp>
    <fileVersion>0.1</fileVersion>
    <cmdowsVersion>0.7</cmdowsVersion>
    <updates>
      <update>
        <modification>KADMOS export of a mdao data graph (MDG).</modification>
        <creator>Imco van Gent</creator>
        <timestamp>2018-02-02T17:58:03.898918</timestamp>
        <fileVersion>0.1</fileVersion>
        <cmdowsVersion>0.7</cmdowsVersion>
      </update>
    </updates>
    <organization>
      <contacts>
        <contact uID="ivangent">
          <company>TU Delft</company>
          <email>i.vangent@tudelft.nl</email>
          <name>Imco van Gent</name>
        </contact>
        <contact uID="lmuller">
          <company>TU Delft</company>
          <email>l.muller@student.tudelft.nl</email>
          <name>Lukas Muller</name>
        </contact>
      </contacts>
      <organigram>
        <integrators>
          <integrator>
            <contactUID>lmuller</contactUID>
          </integrator>
        </integrators>
        <architects>
          <architect>
            <contactUID>ivangent</contactUID>
          </architect>
          <architect>
            <contactUID>lmuller</contactUID>
          </architect>
        </architects>
      </organigram>
    </organization>
  </header>
  <executableBlocks>
    <designCompetences>
      <designCompetence uID="D1[main][1][1.0]">
        <ID>D1</ID>
        <modeID>main</modeID>
        <instanceID>1</instanceID>
        <version>1.0</version>
        <label>D1</label>
        <inputs>
          <input>
            <parameterUID>/data_schema/geometry/x1</parameterUID>
          </input>
          <input>
            <parameterUID>/data_schema/geometry/z2</parameterUID>
          </input>
          <input>
            <parameterUID>/data_schema/analyses/y2</parameterUID>
          </input>
          <input>
            <parameterUID>/data_schema/settings/c</parameterUID>
          </input>
          <input>
            <parameterUID>/data_schema/geometry/z1</parameterUID>
            <validRanges>
              <limitRange>
                <minimum>-5</minimum>
                <maximum>5.0</maximum>
              </limitRange>
              <listRange>
                <listRangeItem>7.5</listRangeItem>
                <listRangeItem>8</listRangeItem>
              </listRange>
            </validRanges>
          </input>
        </inputs>
        <outputs>
          <output>
            <parameterUID>/data_schema/analyses/y1</parameterUID>
          </output>
          <output>
            <parameterUID>/data_schema/architectureNodes/finalCouplingVariables/data_schemaCopy/analyses/y1</parameterUID>
          </output>
        </outputs>
      </designCompetence>
      <designCompetence uID="D2[main][1][1.0]">
        <ID>D2</ID>
        <modeID>main</modeID>
        <instanceID>1</instanceID>
        <version>1.0</version>
        <label>D2</label>
        <inputs>
          <input>
            <parameterUID>/data_schema/settings/c</parameterUID>
          </input>
          <input>
            <parameterUID>/data_schema/geometry/z1</parameterUID>
          </input>
          <input>
            <parameterUID>/data_schema/architectureNodes/couplingCopyVariables/data_schemaCopy/analyses/y1</parameterUID>
          </input>
          <input>
            <parameterUID>/data_schema/geometry/z2</parameterUID>
          </input>
        </inputs>
        <outputs>
          <output>
            <parameterUID>/data_schema/analyses/y2</parameterUID>
          </output>
        </outputs>
      </designCompetence>
    </designCompetences>
    <mathematicalFunctions>
      <mathematicalFunction uID="A">
        <label>A</label>
        <inputs>
          <input>
            <parameterUID>/data_schema/settings/a</parameterUID>
            <equationLabel>a</equationLabel>
          </input>
        </inputs>
        <outputs>
          <output>
            <parameterUID>/data_schema/settings/c</parameterUID>
            <equations uID="A_equation">
              <equation language="Python">a</equation>
              <equation language="LaTeX">a</equation>
              <equation language="MathML">&lt;math xmlns="http://www.w3.org/1998/Math/MathML"&gt;&lt;mi&gt;a&lt;/mi&gt;&lt;/math&gt;</equation>
            </equations>
          </output>
        </outputs>
      </mathematicalFunction>
      <mathematicalFunction uID="F1">
        <label>F1</label>
        <inputs>
          <input>
            <parameterUID>/data_schema/geometry/x1</parameterUID>
            <equationLabel>x1</equationLabel>
          </input>
          <input>
            <parameterUID>/data_schema/analyses/y1</parameterUID>
            <equationLabel>y1</equationLabel>
          </input>
          <input>
            <parameterUID>/data_schema/analyses/y2</parameterUID>
            <equationLabel>y2</equationLabel>
          </input>
          <input>
            <parameterUID>/data_schema/geometry/z2</parameterUID>
            <equationLabel>z2</equationLabel>
          </input>
        </inputs>
        <outputs>
          <output>
            <parameterUID>/data_schema/analyses/f</parameterUID>
            <equations uID="F1_equation">
              <equation language="Python">x1**2+z2+y1+exp(-y2)</equation>
              <equation language="LaTeX">x1^2+z2+y1+e^{-y2}</equation>
              <equation language="MathML">&lt;math xmlns="http://www.w3.org/1998/Math/MathML"&gt;&lt;mi&gt;x&lt;/mi&gt;&lt;msup&gt;&lt;mn&gt;1&lt;/mn&gt;&lt;mn&gt;2&lt;/mn&gt;&lt;/msup&gt;&lt;mo&gt;+&lt;/mo&gt;&lt;mi&gt;z&lt;/mi&gt;&lt;mn&gt;2&lt;/mn&gt;&lt;mo&gt;+&lt;/mo&gt;&lt;mi&gt;y&lt;/mi&gt;&lt;mn&gt;1&lt;/mn&gt;&lt;mo&gt;+&lt;/mo&gt;&lt;msup&gt;&lt;mi&gt;e&lt;/mi&gt;&lt;mrow&gt;&lt;mo&gt;-&lt;/mo&gt;&lt;mi&gt;y&lt;/mi&gt;&lt;mn&gt;2&lt;/mn&gt;&lt;/mrow&gt;&lt;/msup&gt;&lt;/math&gt;</equation>
            </equations>
          </output>
        </outputs>
      </mathematicalFunction>
      <mathematicalFunction uID="G2">
        <label>G2</label>
        <inputs>
          <input>
            <parameterUID>/data_schema/analyses/y2</parameterUID>
            <equationLabel>y2</equationLabel>
          </input>
        </inputs>
        <outputs>
          <output>
            <parameterUID>/data_schema/analyses/g2</parameterUID>
            <equations uID="G2_equation">
              <equation language="Python">1-y2/24.0</equation>
              <equation language="LaTeX">1-y2/24.0</equation>
              <equation language="MathML">&lt;math xmlns="http://www.w3.org/1998/Math/MathML"&gt;&lt;mn&gt;1&lt;/mn&gt;&lt;mo&gt;-&lt;/mo&gt;&lt;mi&gt;y&lt;/mi&gt;&lt;mn&gt;2&lt;/mn&gt;&lt;mo&gt;/&lt;/mo&gt;&lt;mn&gt;24&lt;/mn&gt;&lt;mo&gt;.&lt;/mo&gt;&lt;mn&gt;0&lt;/mn&gt;&lt;/math&gt;</equation>
            </equations>
          </output>
        </outputs>
      </mathematicalFunction>
      <mathematicalFunction uID="G1">
        <label>G1</label>
        <inputs>
          <input>
            <parameterUID>/data_schema/analyses/y1</parameterUID>
            <equationLabel>y1</equationLabel>
          </input>
        </inputs>
        <outputs>
          <output>
            <parameterUID>/data_schema/analyses/g1</parameterUID>
            <equations uID="G1_equation">
              <equation language="Python">y1/3.16-1</equation>
              <equation language="LaTeX">y1/3.16-1</equation>
              <equation language="MathML">&lt;math xmlns="http://www.w3.org/1998/Math/MathML"&gt;&lt;mi&gt;y&lt;/mi&gt;&lt;mn&gt;1&lt;/mn&gt;&lt;mo&gt;/&lt;/mo&gt;&lt;mn&gt;3&lt;/mn&gt;&lt;mo&gt;.&lt;/mo&gt;&lt;mn&gt;16&lt;/mn&gt;&lt;mo&gt;-&lt;/mo&gt;&lt;mn&gt;1&lt;/mn&gt;&lt;/math&gt;</equation>
            </equations>
          </output>
        </outputs>
      </mathematicalFunction>
    </mathematicalFunctions>
  </executableBlocks>
  <parameters>
    <parameter uID="/data_schema/analyses/g2">
      <label>g2</label>
    </parameter>
    <parameter uID="/data_schema/analyses/g1">
      <label>g1</label>
    </parameter>
    <parameter uID="/data_schema/settings/a">
      <label>a</label>
    </parameter>
    <parameter uID="/data_schema/analyses/f">
      <label>f</label>
    </parameter>
    <parameter uID="/data_schema/geometry/x1">
      <label>x1</label>
    </parameter>
    <parameter uID="/data_schema/settings/c">
      <label>c</label>
    </parameter>
    <parameter uID="/data_schema/analyses/y1">
      <label>y1</label>
    </parameter>
    <parameter uID="/data_schema/analyses/y2">
      <label>y2</label>
    </parameter>
    <parameter uID="/data_schema/geometry/z2">
      <label>z2</label>
    </parameter>
    <parameter uID="/data_schema/geometry/z1">
      <label>z1</label>
    </parameter>
  </parameters>
  <problemDefinition uID="converged-MDAGauss-Seidel">
    <problemFormulation>
      <mdaoArchitecture>converged-MDA</mdaoArchitecture>
      <convergerType>Gauss-Seidel</convergerType>
      <executableBlocksOrder>
        <executableBlock position="1">A</executableBlock>
        <executableBlock position="2">D2[main][1][1.0]</executableBlock>
        <executableBlock position="3">D1[main][1][1.0]</executableBlock>
        <executableBlock position="4">F1</executableBlock>
        <executableBlock position="5">G2</executableBlock>
        <executableBlock position="6">G1</executableBlock>
      </executableBlocksOrder>
      <allowUnconvergedCouplings>false</allowUnconvergedCouplings>
    </problemFormulation>
    <problemRoles>
      <parameters>
        <stateVariables>
          <stateVariable uID="__statVar__/data_schema/analyses/g2">
            <parameterUID>/data_schema/analyses/g2</parameterUID>
          </stateVariable>
          <stateVariable uID="__statVar__/data_schema/analyses/g1">
            <parameterUID>/data_schema/analyses/g1</parameterUID>
          </stateVariable>
          <stateVariable uID="__statVar__/data_schema/analyses/f">
            <parameterUID>/data_schema/analyses/f</parameterUID>
          </stateVariable>
          <stateVariable uID="__statVar__/data_schema/analyses/y1">
            <parameterUID>/data_schema/analyses/y1</parameterUID>
          </stateVariable>
          <stateVariable uID="__statVar__/data_schema/analyses/y2">
            <parameterUID>/data_schema/analyses/y2</parameterUID>
          </stateVariable>
        </stateVariables>
      </parameters>
      <executableBlocks>
        <preCouplingBlocks>
          <preCouplingBlock>A</preCouplingBlock>
        </preCouplingBlocks>
        <coupledBlocks>
          <coupledBlock>D2[main][1][1.0]</coupledBlock>
          <coupledBlock>D1[main][1][1.0]</coupledBlock>
        </coupledBlocks>
        <postCouplingBlocks>
          <postCouplingBlock>F1</postCouplingBlock>
          <postCouplingBlock>G2</postCouplingBlock>
          <postCouplingBlock>G1</postCouplingBlock>
        </postCouplingBlocks>
      </executableBlocks>
    </problemRoles>
  </problemDefinition>
  <workflow>
    <problemDefinitionUID>converged-MDAGauss-Seidel</problemDefinitionUID>
    <dataGraph>
      <name>XDSM - converged-MDA-GS</name>
      <edges>
        <edge>
          <fromParameterUID>/data_schema/architectureNodes/initialGuessCouplingVariables/data_schemaCopy/analyses/y1</fromParameterUID>
          <toExecutableBlockUID>Converger</toExecutableBlockUID>
        </edge>
        <edge>
          <fromExecutableBlockUID>D1[main][1][1.0]</fromExecutableBlockUID>
          <toParameterUID>/data_schema/analyses/y1</toParameterUID>
        </edge>
        <edge>
          <fromExecutableBlockUID>D1[main][1][1.0]</fromExecutableBlockUID>
          <toParameterUID>/data_schema/architectureNodes/finalCouplingVariables/data_schemaCopy/analyses/y1</toParameterUID>
        </edge>
        <edge>
          <fromExecutableBlockUID>Converger</fromExecutableBlockUID>
          <toParameterUID>/data_schema/architectureNodes/couplingCopyVariables/data_schemaCopy/analyses/y1</toParameterUID>
        </edge>
        <edge>
          <fromParameterUID>/data_schema/analyses/g2</fromParameterUID>
          <toExecutableBlockUID>Coordinator</toExecutableBlockUID>
        </edge>
        <edge>
          <fromParameterUID>/data_schema/analyses/g1</fromParameterUID>
          <toExecutableBlockUID>Coordinator</toExecutableBlockUID>
        </edge>
        <edge>
          <fromExecutableBlockUID>G2</fromExecutableBlockUID>
          <toParameterUID>/data_schema/analyses/g2</toParameterUID>
        </edge>
        <edge>
          <fromExecutableBlockUID>G1</fromExecutableBlockUID>
          <toParameterUID>/data_schema/analyses/g1</toParameterUID>
        </edge>
        <edge>
          <fromParameterUID>/data_schema/geometry/x1</fromParameterUID>
          <toExecutableBlockUID>D1[main][1][1.0]</toExecutableBlockUID>
        </edge>
        <edge>
          <fromParameterUID>/data_schema/geometry/x1</fromParameterUID>
          <toExecutableBlockUID>F1</toExecutableBlockUID>
        </edge>
        <edge>
          <fromParameterUID>/data_schema/settings/c</fromParameterUID>
          <toExecutableBlockUID>D1[main][1][1.0]</toExecutableBlockUID>
        </edge>
        <edge>
          <fromParameterUID>/data_schema/settings/c</fromParameterUID>
          <toExecutableBlockUID>D2[main][1][1.0]</toExecutableBlockUID>
        </edge>
        <edge>
          <fromParameterUID>/data_schema/settings/a</fromParameterUID>
          <toExecutableBlockUID>A</toExecutableBlockUID>
        </edge>
        <edge>
          <fromParameterUID>/data_schema/architectureNodes/finalCouplingVariables/data_schemaCopy/analyses/y1</fromParameterUID>
          <toExecutableBlockUID>Coordinator</toExecutableBlockUID>
        </edge>
        <edge>
          <fromExecutableBlockUID>A</fromExecutableBlockUID>
          <toParameterUID>/data_schema/settings/c</toParameterUID>
        </edge>
        <edge>
          <fromParameterUID>/data_schema/analyses/y1</fromParameterUID>
          <toExecutableBlockUID>F1</toExecutableBlockUID>
        </edge>
        <edge>
          <fromParameterUID>/data_schema/analyses/y1</fromParameterUID>
          <toExecutableBlockUID>Converger</toExecutableBlockUID>
        </edge>
        <edge>
          <fromParameterUID>/data_schema/analyses/y1</fromParameterUID>
          <toExecutableBlockUID>G1</toExecutableBlockUID>
        </edge>
        <edge>
          <fromParameterUID>/data_schema/analyses/y2</fromParameterUID>
          <toExecutableBlockUID>D1[main][1][1.0]</toExecutableBlockUID>
        </edge>
        <edge>
          <fromParameterUID>/data_schema/analyses/y2</fromParameterUID>
          <toExecutableBlockUID>F1</toExecutableBlockUID>
        </edge>
        <edge>
          <fromParameterUID>/data_schema/analyses/y2</fromParameterUID>
          <toExecutableBlockUID>G2</toExecutableBlockUID>
        </edge>
        <edge>
          <fromParameterUID>/data_schema/analyses/y2</fromParameterUID>
          <toExecutableBlockUID>Coordinator</toExecutableBlockUID>
        </edge>
        <edge>
          <fromExecutableBlockUID>D2[main][1][1.0]</fromExecutableBlockUID>
          <toParameterUID>/data_schema/analyses/y2</toParameterUID>
        </edge>
        <edge>
          <fromParameterUID>/data_schema/geometry/z2</fromParameterUID>
          <toExecutableBlockUID>D1[main][1][1.0]</toExecutableBlockUID>
        </edge>
        <edge>
          <fromParameterUID>/data_schema/geometry/z2</fromParameterUID>
          <toExecutableBlockUID>F1</toExecutableBlockUID>
        </edge>
        <edge>
          <fromParameterUID>/data_schema/geometry/z2</fromParameterUID>
          <toExecutableBlockUID>D2[main][1][1.0]</toExecutableBlockUID>
        </edge>
        <edge>
          <fromParameterUID>/data_schema/geometry/z1</fromParameterUID>
          <toExecutableBlockUID>D1[main][1][1.0]</toExecutableBlockUID>
        </edge>
        <edge>
          <fromParameterUID>/data_schema/geometry/z1</fromParameterUID>
          <toExecutableBlockUID>D2[main][1][1.0]</toExecutableBlockUID>
        </edge>
        <edge>
          <fromExecutableBlockUID>F1</fromExecutableBlockUID>
          <toParameterUID>/data_schema/analyses/f</toParameterUID>
        </edge>
        <edge>
          <fromParameterUID>/data_schema/architectureNodes/couplingCopyVariables/data_schemaCopy/analyses/y1</fromParameterUID>
          <toExecutableBlockUID>D2[main][1][1.0]</toExecutableBlockUID>
        </edge>
        <edge>
          <fromParameterUID>/data_schema/analyses/f</fromParameterUID>
          <toExecutableBlockUID>Coordinator</toExecutableBlockUID>
        </edge>
        <edge>
          <fromExecutableBlockUID>Coordinator</fromExecutableBlockUID>
          <toParameterUID>/data_schema/architectureNodes/initialGuessCouplingVariables/data_schemaCopy/analyses/y1</toParameterUID>
        </edge>
        <edge>
          <fromExecutableBlockUID>Coordinator</fromExecutableBlockUID>
          <toParameterUID>/data_schema/geometry/x1</toParameterUID>
        </edge>
        <edge>
          <fromExecutableBlockUID>Coordinator</fromExecutableBlockUID>
          <toParameterUID>/data_schema/geometry/z1</toParameterUID>
        </edge>
        <edge>
          <fromExecutableBlockUID>Coordinator</fromExecutableBlockUID>
          <toParameterUID>/data_schema/settings/a</toParameterUID>
        </edge>
        <edge>
          <fromExecutableBlockUID>Coordinator</fromExecutableBlockUID>
          <toParameterUID>/data_schema/geometry/z2</toParameterUID>
        </edge>
      </edges>
    </dataGraph>
    <processGraph>
      <name>mpg Sellar problem</name>
      <edges>
        <edge>
          <fromExecutableBlockUID>A</fromExecutableBlockUID>
          <toExecutableBlockUID>Converger</toExecutableBlockUID>
          <processStepNumber>2</processStepNumber>
        </edge>
        <edge>
          <fromExecutableBlockUID>F1</fromExecutableBlockUID>
          <toExecutableBlockUID>Coordinator</toExecutableBlockUID>
          <processStepNumber>7</processStepNumber>
        </edge>
        <edge>
          <fromExecutableBlockUID>G2</fromExecutableBlockUID>
          <toExecutableBlockUID>Coordinator</toExecutableBlockUID>
          <processStepNumber>7</processStepNumber>
        </edge>
        <edge>
          <fromExecutableBlockUID>G1</fromExecutableBlockUID>
          <toExecutableBlockUID>Coordinator</toExecutableBlockUID>
          <processStepNumber>7</processStepNumber>
        </edge>
        <edge>
          <fromExecutableBlockUID>D1[main][1][1.0]</fromExecutableBlockUID>
          <toExecutableBlockUID>Converger</toExecutableBlockUID>
          <processStepNumber>5</processStepNumber>
        </edge>
        <edge>
          <fromExecutableBlockUID>Converger</fromExecutableBlockUID>
          <toExecutableBlockUID>F1</toExecutableBlockUID>
          <processStepNumber>6</processStepNumber>
        </edge>
        <edge>
          <fromExecutableBlockUID>Converger</fromExecutableBlockUID>
          <toExecutableBlockUID>G2</toExecutableBlockUID>
          <processStepNumber>6</processStepNumber>
        </edge>
        <edge>
          <fromExecutableBlockUID>Converger</fromExecutableBlockUID>
          <toExecutableBlockUID>G1</toExecutableBlockUID>
          <processStepNumber>6</processStepNumber>
        </edge>
        <edge>
          <fromExecutableBlockUID>Converger</fromExecutableBlockUID>
          <toExecutableBlockUID>D2[main][1][1.0]</toExecutableBlockUID>
          <processStepNumber>3</processStepNumber>
        </edge>
        <edge>
          <fromExecutableBlockUID>D2[main][1][1.0]</fromExecutableBlockUID>
          <toExecutableBlockUID>D1[main][1][1.0]</toExecutableBlockUID>
          <processStepNumber>4</processStepNumber>
        </edge>
        <edge>
          <fromExecutableBlockUID>Coordinator</fromExecutableBlockUID>
          <toExecutableBlockUID>A</toExecutableBlockUID>
          <processStepNumber>1</processStepNumber>
        </edge>
      </edges>
      <nodes>
        <node>
          <referenceUID>A</referenceUID>
          <processStepNumber>1</processStepNumber>
          <diagonalPosition>1</diagonalPosition>
        </node>
        <node>
          <referenceUID>F1</referenceUID>
          <processStepNumber>6</processStepNumber>
          <diagonalPosition>5</diagonalPosition>
        </node>
        <node>
          <referenceUID>G2</referenceUID>
          <processStepNumber>6</processStepNumber>
          <diagonalPosition>6</diagonalPosition>
        </node>
        <node>
          <referenceUID>G1</referenceUID>
          <processStepNumber>6</processStepNumber>
          <diagonalPosition>7</diagonalPosition>
        </node>
        <node>
          <referenceUID>D1[main][1][1.0]</referenceUID>
          <processStepNumber>4</processStepNumber>
          <diagonalPosition>4</diagonalPosition>
        </node>
        <node>
          <referenceUID>Converger</referenceUID>
          <processStepNumber>2</processStepNumber>
          <convergerStepNumber>5</convergerStepNumber>
          <diagonalPosition>2</diagonalPosition>
        </node>
        <node>
          <referenceUID>D2[main][1][1.0]</referenceUID>
          <processStepNumber>3</processStepNumber>
          <diagonalPosition>3</diagonalPosition>
        </node>
        <node>
          <referenceUID>Coordinator</referenceUID>
          <processStepNumber>0</processStepNumber>
          <convergerStepNumber>7</convergerStepNumber>
          <diagonalPosition>0</diagonalPosition>
        </node>
      </nodes>
      <metadata>
        <loopNesting>
          <loopElements>
            <loopElement relatedUID="Coordinator">
              <loopElements>
                <loopElement relatedUID="Converger">
                  <functionElements>
                    <functionElement>D2[main][1][1.0]</functionElement>
                    <functionElement>D1[main][1][1.0]</functionElement>
                  </functionElements>
                </loopElement>
              </loopElements>
              <functionElements>
                <functionElement>A</functionElement>
                <functionElement>F1</functionElement>
                <functionElement>G1</functionElement>
                <functionElement>G2</functionElement>
              </functionElements>
            </loopElement>
          </loopElements>
        </loopNesting>
      </metadata>
    </processGraph>
  </workflow>
  <architectureElements>
    <parameters>
      <initialGuessCouplingVariables>
        <initialGuessCouplingVariable uID="/data_schema/architectureNodes/initialGuessCouplingVariables/data_schemaCopy/analyses/y1">
          <relatedParameterUID>/data_schema/analyses/y1</relatedParameterUID>
          <label>y1^{c0}</label>
        </initialGuessCouplingVariable>
      </initialGuessCouplingVariables>
      <finalCouplingVariables>
        <finalCouplingVariable uID="/data_schema/architectureNodes/finalCouplingVariables/data_schemaCopy/analyses/y1">
          <relatedParameterUID>/data_schema/analyses/y1</relatedParameterUID>
          <label>y1^*</label>
        </finalCouplingVariable>
      </finalCouplingVariables>
      <couplingCopyVariables>
        <couplingCopyVariable uID="/data_schema/architectureNodes/couplingCopyVariables/data_schemaCopy/analyses/y1">
          <relatedParameterUID>/data_schema/analyses/y1</relatedParameterUID>
          <label>y1^c</label>
        </couplingCopyVariable>
      </couplingCopyVariables>
    </parameters>
    <executableBlocks>
      <coordinators>
        <coordinator uID="Coordinator">
          <label>COOR</label>
        </coordinator>
      </coordinators>
      <convergers>
        <converger uID="Converger">
          <label>CONV</label>
        </converger>
      </convergers>
      <preCouplingAnalyses>
        <preCouplingAnalysis>
          <relatedExecutableBlockUID>A</relatedExecutableBlockUID>
        </preCouplingAnalysis>
      </preCouplingAnalyses>
      <coupledAnalyses>
        <coupledAnalysis>
          <relatedExecutableBlockUID>D1[main][1][1.0]</relatedExecutableBlockUID>
        </coupledAnalysis>
        <coupledAnalysis>
          <relatedExecutableBlockUID>D2[main][1][1.0]</relatedExecutableBlockUID>
        </coupledAnalysis>
      </coupledAnalyses>
      <postCouplingAnalyses>
        <postCouplingAnalysis>
          <relatedExecutableBlockUID>G2</relatedExecutableBlockUID>
        </postCouplingAnalysis>
        <postCouplingAnalysis>
          <relatedExecutableBlockUID>G1</relatedExecutableBlockUID>
        </postCouplingAnalysis>
        <postCouplingAnalysis>
          <relatedExecutableBlockUID>F1</relatedExecutableBlockUID>
        </postCouplingAnalysis>
      </postCouplingAnalyses>
    </executableBlocks>
  </architectureElements>
</cmdows>
