<?xml version='1.0' encoding='UTF-8'?>
<cmdows xmlns:xsi="http://www.w3.org/2001/XMLSchema-instance" xsi:noNamespaceSchemaLocation="https://bitbucket.org/imcovangent/cmdows/raw/master/schema/0.7/cmdows.xsd">
  <header>
    <creator>Lukas Mueller</creator>
    <description>RCG CMDOWS file of the super-sonic business jet test case optimization problem</description>
    <timestamp>2018-01-29T09:19:43.611000</timestamp>
    <fileVersion>0.1</fileVersion>
    <cmdowsVersion>0.7</cmdowsVersion>
    <updates>
      <update>
        <modification>KADMOS export of a repository connectivity graph (RCG).</modification>
        <creator>Lukas Mueller</creator>
        <timestamp>2018-01-29T09:19:43.611000</timestamp>
        <fileVersion>0.1</fileVersion>
        <cmdowsVersion>0.7</cmdowsVersion>
      </update>
    </updates>
    <organization>
      <contacts>
        <contact uID="ivangent">
          <company>TU Delft</company>
          <email>i.vangent@tudelft.nl</email>
          <name>Imco van Gent</name>
        </contact>
        <contact uID="lmuller">
          <company>TU Delft</company>
          <email>l.muller@student.tudelft.nl</email>
          <name>Lukas Muller</name>
        </contact>
      </contacts>
      <organigram>
        <integrators>
          <integrator>
            <contactUID>lmuller</contactUID>
          </integrator>
        </integrators>
        <architects>
          <architect>
            <contactUID>ivangent</contactUID>
          </architect>
          <architect>
            <contactUID>lmuller</contactUID>
          </architect>
        </architects>
      </organigram>
    </organization>
  </header>
  <executableBlocks>
    <designCompetences>
      <designCompetence uID="structure[main][1][1.0]">
        <ID>structure</ID>
        <modeID>main</modeID>
        <instanceID>1</instanceID>
        <version>1.0</version>
        <label>structure</label>
        <inputs>
          <input>
            <parameterUID>/data_schema/aircraft/geometry/Lambda</parameterUID>
          </input>
          <input>
            <parameterUID>/data_schema/aircraft/geometry/Sref</parameterUID>
          </input>
          <input>
            <parameterUID>/data_schema/aircraft/geometry/AR</parameterUID>
          </input>
          <input>
            <parameterUID>/data_schema/aircraft/other/L</parameterUID>
          </input>
          <input>
            <parameterUID>/data_schema/aircraft/geometry/tc</parameterUID>
          </input>
          <input>
            <parameterUID>/data_schema/aircraft/geometry/lambda</parameterUID>
          </input>
          <input>
            <parameterUID>/data_schema/aircraft/geometry/section</parameterUID>
          </input>
          <input>
            <parameterUID>/data_schema/aircraft/weight/WE</parameterUID>
          </input>
        </inputs>
        <outputs>
          <output>
            <parameterUID>/data_schema/aircraft/geometry/Theta</parameterUID>
          </output>
          <output>
            <parameterUID>/data_schema/aircraft/weight/WT</parameterUID>
          </output>
          <output>
            <parameterUID>/data_schema/aircraft/other/sigma</parameterUID>
          </output>
          <output>
            <parameterUID>/data_schema/aircraft/weight/WF</parameterUID>
          </output>
        </outputs>
        <metadata>
          <generalInfo>
            <owner>
              <contactUID>remilafage</contactUID>
            </owner>
            <description>Weight estimation of different aircraft parts.</description>
            <creator>
              <contactUID>sylvaindubreuil</contactUID>
            </creator>
          </generalInfo>
        </metadata>
      </designCompetence>
      <designCompetence uID="aerodynamics[main][1][1.0]">
        <ID>aerodynamics</ID>
        <modeID>main</modeID>
        <instanceID>1</instanceID>
        <version>1.0</version>
        <label>aerodynamics</label>
        <inputs>
          <input>
            <parameterUID>/data_schema/reference/h</parameterUID>
          </input>
          <input>
            <parameterUID>/data_schema/aircraft/geometry/Sref</parameterUID>
          </input>
          <input>
            <parameterUID>/data_schema/reference/ESF</parameterUID>
          </input>
          <input>
            <parameterUID>/data_schema/aircraft/geometry/AR</parameterUID>
          </input>
          <input>
            <parameterUID>/data_schema/aircraft/other/Cf</parameterUID>
          </input>
          <input>
            <parameterUID>/data_schema/aircraft/weight/WT</parameterUID>
          </input>
          <input>
            <parameterUID>/data_schema/aircraft/geometry/tc</parameterUID>
          </input>
          <input>
            <parameterUID>/data_schema/reference/M</parameterUID>
          </input>
          <input>
            <parameterUID>/data_schema/aircraft/geometry/Lambda</parameterUID>
          </input>
          <input>
            <parameterUID>/data_schema/aircraft/geometry/Theta</parameterUID>
          </input>
        </inputs>
        <outputs>
          <output>
            <parameterUID>/data_schema/aircraft/other/fin</parameterUID>
          </output>
          <output>
            <parameterUID>/data_schema/aircraft/other/D</parameterUID>
          </output>
          <output>
            <parameterUID>/data_schema/aircraft/other/dpdx</parameterUID>
          </output>
          <output>
            <parameterUID>/data_schema/aircraft/other/L</parameterUID>
          </output>
        </outputs>
        <metadata>
          <generalInfo>
            <owner>
              <contactUID>remilafage</contactUID>
            </owner>
            <description>Estimation of the aircraft lift and drag during cruise.</description>
            <creator>
              <contactUID>sylvaindubreuil</contactUID>
            </creator>
          </generalInfo>
        </metadata>
      </designCompetence>
      <designCompetence uID="propulsion[main][1][1.0]">
        <ID>propulsion</ID>
        <modeID>main</modeID>
        <instanceID>1</instanceID>
        <version>1.0</version>
        <label>propulsion</label>
        <inputs>
          <input>
            <parameterUID>/data_schema/reference/h</parameterUID>
          </input>
          <input>
            <parameterUID>/data_schema/aircraft/other/D</parameterUID>
          </input>
          <input>
            <parameterUID>/data_schema/reference/M</parameterUID>
          </input>
          <input>
            <parameterUID>/data_schema/aircraft/other/T</parameterUID>
          </input>
        </inputs>
        <outputs>
          <output>
            <parameterUID>/data_schema/reference/ESF</parameterUID>
          </output>
          <output>
            <parameterUID>/data_schema/reference/Temp</parameterUID>
          </output>
          <output>
            <parameterUID>/data_schema/aircraft/other/DT</parameterUID>
          </output>
          <output>
            <parameterUID>/data_schema/aircraft/weight/WE</parameterUID>
          </output>
          <output>
            <parameterUID>/data_schema/aircraft/other/SFC</parameterUID>
          </output>
        </outputs>
        <metadata>
          <generalInfo>
            <owner>
              <contactUID>remilafage</contactUID>
            </owner>
            <description>Engine sizing and estimation of the engine thrust.</description>
            <creator>
              <contactUID>sylvaindubreuil</contactUID>
            </creator>
          </generalInfo>
        </metadata>
      </designCompetence>
      <designCompetence uID="performance[main][1][1.0]">
        <ID>performance</ID>
        <modeID>main</modeID>
        <instanceID>1</instanceID>
        <version>1.0</version>
        <label>performance</label>
        <inputs>
          <input>
            <parameterUID>/data_schema/aircraft/other/SFC</parameterUID>
          </input>
          <input>
            <parameterUID>/data_schema/aircraft/weight/WT</parameterUID>
          </input>
          <input>
            <parameterUID>/data_schema/reference/h</parameterUID>
          </input>
          <input>
            <parameterUID>/data_schema/reference/M</parameterUID>
          </input>
          <input>
            <parameterUID>/data_schema/aircraft/other/fin</parameterUID>
          </input>
          <input>
            <parameterUID>/data_schema/aircraft/weight/WF</parameterUID>
          </input>
        </inputs>
        <outputs>
          <output>
            <parameterUID>/data_schema/aircraft/other/R</parameterUID>
          </output>
        </outputs>
        <metadata>
          <generalInfo>
            <owner>
              <contactUID>remilafage</contactUID>
            </owner>
            <description>Estimation of the aircraft range.</description>
            <creator>
              <contactUID>sylvaindubreuil</contactUID>
            </creator>
          </generalInfo>
        </metadata>
      </designCompetence>
    </designCompetences>
    <mathematicalFunctions>
      <mathematicalFunction uID="objective">
        <label>objective</label>
        <inputs>
          <input>
            <parameterUID>/data_schema/aircraft/other/R</parameterUID>
            <equationLabel>R</equationLabel>
          </input>
        </inputs>
        <outputs>
          <output>
            <parameterUID>/data_schema/aircraft/other/objective</parameterUID>
            <equations uID="objective_equation">
              <equation language="Python">-R</equation>
              <equation language="LaTeX">-R</equation>
            </equations>
          </output>
        </outputs>
      </mathematicalFunction>
    </mathematicalFunctions>
  </executableBlocks>
  <parameters>
    <parameter uID="/data_schema/aircraft/geometry/Theta">
      <label>Theta</label>
    </parameter>
    <parameter uID="/data_schema/aircraft/weight/WE">
      <label>WE</label>
    </parameter>
    <parameter uID="/data_schema/aircraft/weight/WF">
      <label>WF</label>
    </parameter>
    <parameter uID="/data_schema/aircraft/other/L">
      <label>L</label>
    </parameter>
    <parameter uID="/data_schema/reference/ESF">
      <label>ESF</label>
    </parameter>
    <parameter uID="/data_schema/aircraft/other/SFC">
      <label>SFC</label>
    </parameter>
    <parameter uID="/data_schema/aircraft/other/D">
      <label>D</label>
    </parameter>
    <parameter uID="/data_schema/aircraft/other/R">
      <label>R</label>
    </parameter>
    <parameter uID="/data_schema/aircraft/other/fin">
      <label>fin</label>
    </parameter>
    <parameter uID="/data_schema/aircraft/weight/WT">
      <label>WT</label>
    </parameter>
    <parameter uID="/data_schema/aircraft/other/Cf">
      <label>Cf</label>
    </parameter>
    <parameter uID="/data_schema/aircraft/geometry/lambda">
      <label>lambda</label>
    </parameter>
    <parameter uID="/data_schema/aircraft/geometry/section">
      <label>section</label>
    </parameter>
    <parameter uID="/data_schema/aircraft/other/T">
      <label>T</label>
    </parameter>
    <parameter uID="/data_schema/aircraft/other/dpdx">
      <label>dpdx</label>
    </parameter>
    <parameter uID="/data_schema/aircraft/other/DT">
      <label>DT</label>
    </parameter>
    <parameter uID="/data_schema/aircraft/other/sigma">
      <label>sigma</label>
    </parameter>
    <parameter uID="/data_schema/aircraft/other/objective">
      <label>obj</label>
    </parameter>
    <parameter uID="/data_schema/reference/Temp">
      <label>Temp</label>
    </parameter>
    <parameter uID="/data_schema/aircraft/geometry/AR">
      <label>AR</label>
    </parameter>
    <parameter uID="/data_schema/aircraft/geometry/Sref">
      <label>Sref</label>
    </parameter>
    <parameter uID="/data_schema/reference/h">
      <label>h</label>
    </parameter>
    <parameter uID="/data_schema/aircraft/geometry/tc">
      <label>tc</label>
    </parameter>
    <parameter uID="/data_schema/reference/M">
      <label>M</label>
    </parameter>
    <parameter uID="/data_schema/aircraft/geometry/Lambda">
      <label>Lambda</label>
    </parameter>
  </parameters>
  <workflow>
    <dataGraph>
      <name>RCG</name>
      <edges>
        <edge>
          <fromParameterUID>/data_schema/aircraft/other/Cf</fromParameterUID>
          <toExecutableBlockUID>aerodynamics[main][1][1.0]</toExecutableBlockUID>
        </edge>
        <edge>
          <fromParameterUID>/data_schema/aircraft/geometry/lambda</fromParameterUID>
          <toExecutableBlockUID>structure[main][1][1.0]</toExecutableBlockUID>
        </edge>
        <edge>
          <fromParameterUID>/data_schema/aircraft/geometry/section</fromParameterUID>
          <toExecutableBlockUID>structure[main][1][1.0]</toExecutableBlockUID>
        </edge>
        <edge>
          <fromParameterUID>/data_schema/aircraft/geometry/Theta</fromParameterUID>
          <toExecutableBlockUID>aerodynamics[main][1][1.0]</toExecutableBlockUID>
        </edge>
        <edge>
          <fromParameterUID>/data_schema/aircraft/geometry/AR</fromParameterUID>
          <toExecutableBlockUID>structure[main][1][1.0]</toExecutableBlockUID>
        </edge>
        <edge>
          <fromParameterUID>/data_schema/aircraft/geometry/AR</fromParameterUID>
          <toExecutableBlockUID>aerodynamics[main][1][1.0]</toExecutableBlockUID>
        </edge>
        <edge>
          <fromExecutableBlockUID>structure[main][1][1.0]</fromExecutableBlockUID>
          <toParameterUID>/data_schema/aircraft/geometry/Theta</toParameterUID>
        </edge>
        <edge>
          <fromExecutableBlockUID>structure[main][1][1.0]</fromExecutableBlockUID>
          <toParameterUID>/data_schema/aircraft/weight/WT</toParameterUID>
        </edge>
        <edge>
          <fromExecutableBlockUID>structure[main][1][1.0]</fromExecutableBlockUID>
          <toParameterUID>/data_schema/aircraft/other/sigma</toParameterUID>
        </edge>
        <edge>
          <fromExecutableBlockUID>structure[main][1][1.0]</fromExecutableBlockUID>
          <toParameterUID>/data_schema/aircraft/weight/WF</toParameterUID>
        </edge>
        <edge>
          <fromExecutableBlockUID>objective</fromExecutableBlockUID>
          <toParameterUID>/data_schema/aircraft/other/objective</toParameterUID>
        </edge>
        <edge>
          <fromExecutableBlockUID>aerodynamics[main][1][1.0]</fromExecutableBlockUID>
          <toParameterUID>/data_schema/aircraft/other/fin</toParameterUID>
        </edge>
        <edge>
          <fromExecutableBlockUID>aerodynamics[main][1][1.0]</fromExecutableBlockUID>
          <toParameterUID>/data_schema/aircraft/other/D</toParameterUID>
        </edge>
        <edge>
          <fromExecutableBlockUID>aerodynamics[main][1][1.0]</fromExecutableBlockUID>
          <toParameterUID>/data_schema/aircraft/other/dpdx</toParameterUID>
        </edge>
        <edge>
          <fromExecutableBlockUID>aerodynamics[main][1][1.0]</fromExecutableBlockUID>
          <toParameterUID>/data_schema/aircraft/other/L</toParameterUID>
        </edge>
        <edge>
          <fromParameterUID>/data_schema/aircraft/geometry/Sref</fromParameterUID>
          <toExecutableBlockUID>structure[main][1][1.0]</toExecutableBlockUID>
        </edge>
        <edge>
          <fromParameterUID>/data_schema/aircraft/geometry/Sref</fromParameterUID>
          <toExecutableBlockUID>aerodynamics[main][1][1.0]</toExecutableBlockUID>
        </edge>
        <edge>
          <fromParameterUID>/data_schema/aircraft/weight/WT</fromParameterUID>
          <toExecutableBlockUID>aerodynamics[main][1][1.0]</toExecutableBlockUID>
        </edge>
        <edge>
          <fromParameterUID>/data_schema/aircraft/weight/WT</fromParameterUID>
          <toExecutableBlockUID>performance[main][1][1.0]</toExecutableBlockUID>
        </edge>
        <edge>
          <fromParameterUID>/data_schema/reference/h</fromParameterUID>
          <toExecutableBlockUID>aerodynamics[main][1][1.0]</toExecutableBlockUID>
        </edge>
        <edge>
          <fromParameterUID>/data_schema/reference/h</fromParameterUID>
          <toExecutableBlockUID>propulsion[main][1][1.0]</toExecutableBlockUID>
        </edge>
        <edge>
          <fromParameterUID>/data_schema/reference/h</fromParameterUID>
          <toExecutableBlockUID>performance[main][1][1.0]</toExecutableBlockUID>
        </edge>
        <edge>
          <fromParameterUID>/data_schema/aircraft/weight/WE</fromParameterUID>
          <toExecutableBlockUID>structure[main][1][1.0]</toExecutableBlockUID>
        </edge>
        <edge>
          <fromParameterUID>/data_schema/aircraft/weight/WF</fromParameterUID>
          <toExecutableBlockUID>performance[main][1][1.0]</toExecutableBlockUID>
        </edge>
        <edge>
          <fromParameterUID>/data_schema/aircraft/geometry/tc</fromParameterUID>
          <toExecutableBlockUID>structure[main][1][1.0]</toExecutableBlockUID>
        </edge>
        <edge>
          <fromParameterUID>/data_schema/aircraft/geometry/tc</fromParameterUID>
          <toExecutableBlockUID>aerodynamics[main][1][1.0]</toExecutableBlockUID>
        </edge>
        <edge>
          <fromParameterUID>/data_schema/aircraft/other/L</fromParameterUID>
          <toExecutableBlockUID>structure[main][1][1.0]</toExecutableBlockUID>
        </edge>
        <edge>
          <fromParameterUID>/data_schema/reference/ESF</fromParameterUID>
          <toExecutableBlockUID>aerodynamics[main][1][1.0]</toExecutableBlockUID>
        </edge>
        <edge>
          <fromExecutableBlockUID>performance[main][1][1.0]</fromExecutableBlockUID>
          <toParameterUID>/data_schema/aircraft/other/R</toParameterUID>
        </edge>
        <edge>
          <fromParameterUID>/data_schema/aircraft/other/SFC</fromParameterUID>
          <toExecutableBlockUID>performance[main][1][1.0]</toExecutableBlockUID>
        </edge>
        <edge>
          <fromParameterUID>/data_schema/aircraft/other/D</fromParameterUID>
          <toExecutableBlockUID>propulsion[main][1][1.0]</toExecutableBlockUID>
        </edge>
        <edge>
          <fromParameterUID>/data_schema/reference/M</fromParameterUID>
          <toExecutableBlockUID>aerodynamics[main][1][1.0]</toExecutableBlockUID>
        </edge>
        <edge>
          <fromParameterUID>/data_schema/reference/M</fromParameterUID>
          <toExecutableBlockUID>propulsion[main][1][1.0]</toExecutableBlockUID>
        </edge>
        <edge>
          <fromParameterUID>/data_schema/reference/M</fromParameterUID>
          <toExecutableBlockUID>performance[main][1][1.0]</toExecutableBlockUID>
        </edge>
        <edge>
          <fromParameterUID>/data_schema/aircraft/geometry/Lambda</fromParameterUID>
          <toExecutableBlockUID>structure[main][1][1.0]</toExecutableBlockUID>
        </edge>
        <edge>
          <fromParameterUID>/data_schema/aircraft/geometry/Lambda</fromParameterUID>
          <toExecutableBlockUID>aerodynamics[main][1][1.0]</toExecutableBlockUID>
        </edge>
        <edge>
          <fromParameterUID>/data_schema/aircraft/other/R</fromParameterUID>
          <toExecutableBlockUID>objective</toExecutableBlockUID>
        </edge>
        <edge>
          <fromParameterUID>/data_schema/aircraft/other/fin</fromParameterUID>
          <toExecutableBlockUID>performance[main][1][1.0]</toExecutableBlockUID>
        </edge>
        <edge>
          <fromExecutableBlockUID>propulsion[main][1][1.0]</fromExecutableBlockUID>
          <toParameterUID>/data_schema/reference/ESF</toParameterUID>
        </edge>
        <edge>
          <fromExecutableBlockUID>propulsion[main][1][1.0]</fromExecutableBlockUID>
          <toParameterUID>/data_schema/reference/Temp</toParameterUID>
        </edge>
        <edge>
          <fromExecutableBlockUID>propulsion[main][1][1.0]</fromExecutableBlockUID>
          <toParameterUID>/data_schema/aircraft/other/DT</toParameterUID>
        </edge>
        <edge>
          <fromExecutableBlockUID>propulsion[main][1][1.0]</fromExecutableBlockUID>
          <toParameterUID>/data_schema/aircraft/weight/WE</toParameterUID>
        </edge>
        <edge>
          <fromExecutableBlockUID>propulsion[main][1][1.0]</fromExecutableBlockUID>
          <toParameterUID>/data_schema/aircraft/other/SFC</toParameterUID>
        </edge>
        <edge>
          <fromParameterUID>/data_schema/aircraft/other/T</fromParameterUID>
          <toExecutableBlockUID>propulsion[main][1][1.0]</toExecutableBlockUID>
        </edge>
      </edges>
    </dataGraph>
  </workflow>
</cmdows>
